{
    "functions": [
        {
            "function": "minecraft:reference",
            "name": "tf2:load_crossbow",
            "conditions": [
                {
                    "condition": "minecraft:entity_scores",
                    "entity": "this",
                    "scores": {
                        "tf2.attack_delay": {
                            "min": -2147483648,
                            "max": 1000
                        }
                    }
                },
                {
                    "condition": "minecraft:reference",
                    "name": "tf2:ammo_in_clip"
                }
            ]
        }
    ],
    "pools": [
        {
            "rolls": 1,
            "entries": [
                {
                    "type": "minecraft:item",
                    "name": "minecraft:crossbow",
                    "functions": [
                        {
                            "function": "minecraft:set_name",
                            "name": {
                                "text": "Pistol",
                                "color": "gray",
                                "italic": true
                            }
                        },
                        {
                            "function": "minecraft:set_nbt",
                            "tag": "{\n                                CustomModelData: 32000,\n                                retina: {HorizontalCount: 1, VerticalCount: 1, CenteredCount: 0, EndpointEntity: true, TargetEntities: true, SpreadFactor: [40, 85], MaxRecursionDepth: 100},\n                                attributes: {damage: {base: 15}, attackDelay: 0.15d, reloadDelay: [1.005d, 1.005d], clip: 12, ammo: 40},\n                                controls: {main_fire: true, alt_fire: false, reload: 3},\n                                Charged: 0b, Unbreakable: 1b\n                            }"
                        }
                    ]
                }
            ]
        }
    ]
}