{
    "type": "minecraft:multi_action",
    "title": "Disguise Kit",
    "can_close_with_escape": false,
    "columns": 9,
    "body": [
        {
            "type": "minecraft:plain_message",
            "contents": {
                "text": "\ue213_\ue214_\ue217_\ue215_\ue216_\ue218_\ue219_\ue212_\ue211_\n\n\n",
                "font": "tf2:head_viewmodel"
            },
            "width": 550
        }
    ],
    "actions": [
        {
            "label": {
                "text": "Scout",
                "color": "#D95A58"
            },
            "width": 55,
            "action": {
                "type": "minecraft:run_command",
                "command": "trigger tf2.disguise set 13"
            }
        },
        {
            "label": {
                "text": "Soldier",
                "color": "#D95A58"
            },
            "width": 55,
            "action": {
                "type": "minecraft:run_command",
                "command": "trigger tf2.disguise set 14"
            }
        },
        {
            "label": {
                "text": "Pyro",
                "color": "#D95A58"
            },
            "width": 55,
            "action": {
                "type": "minecraft:run_command",
                "command": "trigger tf2.disguise set 17"
            }
        },
        {
            "label": {
                "text": "Demoman",
                "color": "#D95A58"
            },
            "width": 55,
            "action": {
                "type": "minecraft:run_command",
                "command": "trigger tf2.disguise set 15"
            }
        },
        {
            "label": {
                "text": "Heavy",
                "color": "#D95A58"
            },
            "width": 55,
            "action": {
                "type": "minecraft:run_command",
                "command": "trigger tf2.disguise set 16"
            }
        },
        {
            "label": {
                "text": "Engineer",
                "color": "#D95A58"
            },
            "width": 55,
            "action": {
                "type": "minecraft:run_command",
                "command": "trigger tf2.disguise set 18"
            }
        },
        {
            "label": {
                "text": "Medic",
                "color": "#D95A58"
            },
            "width": 55,
            "action": {
                "type": "minecraft:run_command",
                "command": "trigger tf2.disguise set 19"
            }
        },
        {
            "label": {
                "text": "Sniper",
                "color": "#D95A58"
            },
            "width": 55,
            "action": {
                "type": "minecraft:run_command",
                "command": "trigger tf2.disguise set 12"
            }
        },
        {
            "label": {
                "text": "Spy",
                "color": "#D95A58"
            },
            "width": 55,
            "action": {
                "type": "minecraft:run_command",
                "command": "trigger tf2.disguise set 11"
            }
        },
        {
            "label": [
                {
                    "text": "Disguise as "
                },
                {
                    "text": "BLU",
                    "color": "blue"
                }
            ],
            "action": {
                "type": "minecraft:show_dialog",
                "dialog": "tf2:blu_disguise"
            }
        }
    ]
}